{
 "attach_print": 0,
 "channel": "Email",
 "condition": "doc.workflow_state == \"Approved\"",
 "creation": "2024-07-30 08:23:08.478172",
 "days_in_advance": 0,
 "docstatus": 0,
 "doctype": "Notification",
 "document_type": "Fuel Delivery Request Approval",
 "enabled": 0,
 "event": "Custom",
 "idx": 0,
 "is_standard": 1,
 "message": "<p>Add your message here</p>\n",
 "message_type": "Markdown",
 "modified": "2024-07-30 08:48:35.240264",
 "modified_by": "Administrator",
 "module": "Fuel Management",
 "name": "Fuel Delivery Request Approval Granted",
 "owner": "Administrator",
 "recipients": [
  {
   "receiver_by_role": "All"
  }
 ],
 "send_system_notification": 1,
 "send_to_all_assignees": 0,
 "subject": "Fuel Delivery Request Approval {{doc.name}} Granted. Initiate Fuel Delivery Process.",
 "value_changed": "workflow_state"
}